piservo/__init__.py
piservo/servo.py
piServoCtl-1.1.0.dist-info/LICENSE
piServoCtl-1.1.0.dist-info/METADATA
piServoCtl-1.1.0.dist-info/WHEEL
piServoCtl-1.1.0.dist-info/top_level.txt
piServoCtl-1.1.0.dist-info/RECORD
