Metadata-Version: 2.1
Name: piServoCtl
Version: 1.1.0
Summary: This is a servo motor control library for Raspberry Pi.
Home-page: https://github.com/naoto64/piServoCtl
Author: naoto64
Author-email: naoto64.2000@gmail.com
License: MIT License
Keywords: Servo Motor PWM Control RaspberryPi
Platform: UNKNOWN
Classifier: Development Status :: 5 - Production/Stable
Classifier: License :: OSI Approved :: MIT License
Classifier: Programming Language :: Python
Classifier: Programming Language :: Python :: 3
Classifier: Programming Language :: Python :: 3.4
Classifier: Programming Language :: Python :: 3.5
Classifier: Programming Language :: Python :: 3.6
Classifier: Programming Language :: Python :: 3.7
Classifier: Topic :: Scientific/Engineering
Classifier: Topic :: Software Development :: Libraries :: Python Modules
Requires-Dist: pigpio (==1.44)
